dvrd_smtp/__init__.py
dvrd_smtp/types.py
dvrd_smtp/models/__init__.py
dvrd_smtp/models/smtp_message.py
dvrd_smtp/models/smtp_server.py
dvrd_smtp-1.1.7.dist-info/LICENSE
dvrd_smtp-1.1.7.dist-info/METADATA
dvrd_smtp-1.1.7.dist-info/WHEEL
dvrd_smtp-1.1.7.dist-info/top_level.txt
dvrd_smtp-1.1.7.dist-info/RECORD
