Metadata-Version: 2.2
Name: dvrd_smtp
Version: 1.1.7
Summary: Object oriented wrapper for smtplib
Author-email: Dave van Rijn Development <develop@davevanrijn.nl>
Project-URL: Homepage, https://bitbucket.org/Naampie/dvrd-smtp
Project-URL: Issues, https://bitbucket.org/Naampie/dvrd-smtp/issues
Classifier: Programming Language :: Python :: 3.11
Classifier: License :: OSI Approved :: BSD License
Classifier: Operating System :: OS Independent
Requires-Python: >=3.11
License-File: LICENSE
Provides-Extra: dkim
Requires-Dist: dkimpy; extra == "dkim"
